[
    {
        "date": "26/Sep",
        "team_1": "NYG",
        "score_1": 15,
        "score_2": 20,
        "team_2": "DAL",
        "game_url": "usa/nfl/new-york-giants-dallas-cowboys-CIpOBlzq/"
    },
    {
        "date": "22/Sep",
        "team_1": "CLE",
        "score_1": 15,
        "score_2": 21,
        "team_2": "NYG",
        "game_url": "usa/nfl/cleveland-browns-new-york-giants-GWStxime/"
    },
    {
        "date": "15/Sep",
        "team_1": "WSH",
        "score_1": 21,
        "score_2": 18,
        "team_2": "NYG",
        "game_url": "usa/nfl/washington-commanders-new-york-giants-r1DTUZuS/"
    },
    {
        "date": "08/Sep",
        "team_1": "NYG",
        "score_1": 6,
        "score_2": 28,
        "team_2": "MIN",
        "game_url": "usa/nfl/new-york-giants-minnesota-vikings-xrJMNuBm/"
    },
    {
        "date": "24/Aug",
        "team_1": "NYJ",
        "score_1": 10,
        "score_2": 6,
        "team_2": "NYG",
        "game_url": "usa/nfl/new-york-jets-new-york-giants-hWpDojZ9/"
    },
    {
        "date": "17/Aug",
        "team_1": "HOU",
        "score_1": 28,
        "score_2": 10,
        "team_2": "NYG",
        "game_url": "usa/nfl/houston-texans-new-york-giants-CW9cBczq/"
    },
    {
        "date": "08/Aug",
        "team_1": "NYG",
        "score_1": 14,
        "score_2": 3,
        "team_2": "DET",
        "game_url": "usa/nfl/new-york-giants-detroit-lions-nZV8ZUNO/"
    },
    {
        "date": "07/Jan",
        "team_1": "NYG",
        "score_1": 27,
        "score_2": 10,
        "team_2": "PHI",
        "game_url": "usa/nfl-2023-2024/new-york-giants-philadelphia-eagles-bajbFABq/"
    },
    {
        "date": "31/Dec",
        "team_1": "NYG",
        "score_1": 25,
        "score_2": 26,
        "team_2": "LAR",
        "game_url": "usa/nfl-2023-2024/new-york-giants-los-angeles-rams-vyNG6tTB/"
    },
    {
        "date": "25/Dec",
        "team_1": "PHI",
        "score_1": 33,
        "score_2": 25,
        "team_2": "NYG",
        "game_url": "usa/nfl-2023-2024/philadelphia-eagles-new-york-giants-dzbko58Q/"
    },
    {
        "date": "17/Dec",
        "team_1": "NO",
        "score_1": 24,
        "score_2": 6,
        "team_2": "NYG",
        "game_url": "usa/nfl-2023-2024/new-orleans-saints-new-york-giants-pd0ZxB8E/"
    },
    {
        "date": "11/Dec",
        "team_1": "NYG",
        "score_1": 24,
        "score_2": 22,
        "team_2": "GB",
        "game_url": "usa/nfl-2023-2024/new-york-giants-green-bay-packers-rXJvHToe/"
    },
    {
        "date": "26/Nov",
        "team_1": "NYG",
        "score_1": 10,
        "score_2": 7,
        "team_2": "NE",
        "game_url": "usa/nfl-2023-2024/new-york-giants-new-england-patriots-YaVba4Kh/"
    },
    {
        "date": "19/Nov",
        "team_1": "WSH",
        "score_1": 19,
        "score_2": 31,
        "team_2": "NYG",
        "game_url": "usa/nfl-2023-2024/washington-commanders-new-york-giants-nNgrM6A8/"
    },
    {
        "date": "12/Nov",
        "team_1": "DAL",
        "score_1": 49,
        "score_2": 17,
        "team_2": "NYG",
        "game_url": "usa/nfl-2023-2024/dallas-cowboys-new-york-giants-fDtsg8tM/"
    },
    {
        "date": "05/Nov",
        "team_1": "LV",
        "score_1": 30,
        "score_2": 6,
        "team_2": "NYG",
        "game_url": "usa/nfl-2023-2024/las-vegas-raiders-new-york-giants-jwFmqXCc/"
    },
    {
        "date": "29/Oct",
        "team_1": "NYG",
        "score_1": 10,
        "score_2": 13,
        "team_2": "NYJ",
        "game_url": "usa/nfl-2023-2024/new-york-giants-new-york-jets-O6wYVMxs/"
    },
    {
        "date": "22/Oct",
        "team_1": "NYG",
        "score_1": 14,
        "score_2": 7,
        "team_2": "WSH",
        "game_url": "usa/nfl-2023-2024/new-york-giants-washington-commanders-QcWY02w7/"
    },
    {
        "date": "15/Oct",
        "team_1": "BUF",
        "score_1": 14,
        "score_2": 9,
        "team_2": "NYG",
        "game_url": "usa/nfl-2023-2024/buffalo-bills-new-york-giants-rBbsBn1E/"
    },
    {
        "date": "08/Oct",
        "team_1": "MIA",
        "score_1": 31,
        "score_2": 16,
        "team_2": "NYG",
        "game_url": "usa/nfl-2023-2024/miami-dolphins-new-york-giants-2N3ObIBi/"
    },
    {
        "date": "02/Oct",
        "team_1": "NYG",
        "score_1": 3,
        "score_2": 24,
        "team_2": "SEA",
        "game_url": "usa/nfl-2023-2024/new-york-giants-seattle-seahawks-tAYi5xJH/"
    },
    {
        "date": "21/Sep",
        "team_1": "SF",
        "score_1": 30,
        "score_2": 12,
        "team_2": "NYG",
        "game_url": "usa/nfl-2023-2024/san-francisco-49ers-new-york-giants-K05hTr60/"
    },
    {
        "date": "17/Sep",
        "team_1": "ARI",
        "score_1": 28,
        "score_2": 31,
        "team_2": "NYG",
        "game_url": "usa/nfl-2023-2024/arizona-cardinals-new-york-giants-rH7LQkp2/"
    },
    {
        "date": "10/Sep",
        "team_1": "NYG",
        "score_1": 0,
        "score_2": 40,
        "team_2": "DAL",
        "game_url": "usa/nfl-2023-2024/new-york-giants-dallas-cowboys-UVYvEC0d/"
    },
    {
        "date": "26/Aug",
        "team_1": "NYG",
        "score_1": 24,
        "score_2": 32,
        "team_2": "NYJ",
        "game_url": "usa/nfl-2023-2024/new-york-giants-new-york-jets-nRcGza3G/"
    },
    {
        "date": "18/Aug",
        "team_1": "NYG",
        "score_1": 21,
        "score_2": 19,
        "team_2": "CAR",
        "game_url": "usa/nfl-2023-2024/new-york-giants-carolina-panthers-IigCyulA/"
    },
    {
        "date": "11/Aug",
        "team_1": "DET",
        "score_1": 21,
        "score_2": 16,
        "team_2": "NYG",
        "game_url": "usa/nfl-2023-2024/detroit-lions-new-york-giants-h8EDGwCp/"
    },
    {
        "date": "21/Jan",
        "team_1": "PHI",
        "score_1": 38,
        "score_2": 7,
        "team_2": "NYG",
        "game_url": "usa/nfl-2022-2023/philadelphia-eagles-new-york-giants-fk4jcXDt/"
    },
    {
        "date": "15/Jan",
        "team_1": "MIN",
        "score_1": 24,
        "score_2": 31,
        "team_2": "NYG",
        "game_url": "usa/nfl-2022-2023/minnesota-vikings-new-york-giants-nqPkMmo6/"
    },
    {
        "date": "08/Jan",
        "team_1": "PHI",
        "score_1": 22,
        "score_2": 16,
        "team_2": "NYG",
        "game_url": "usa/nfl-2022-2023/philadelphia-eagles-new-york-giants-OnyeAadA/"
    },
    {
        "date": "01/Jan",
        "team_1": "NYG",
        "score_1": 38,
        "score_2": 10,
        "team_2": "IND",
        "game_url": "usa/nfl-2022-2023/new-york-giants-indianapolis-colts-YNBzqmON/"
    },
    {
        "date": "24/Dec",
        "team_1": "MIN",
        "score_1": 27,
        "score_2": 24,
        "team_2": "NYG",
        "game_url": "usa/nfl-2022-2023/minnesota-vikings-new-york-giants-M3l9tf2P/"
    },
    {
        "date": "18/Dec",
        "team_1": "WSH",
        "score_1": 12,
        "score_2": 20,
        "team_2": "NYG",
        "game_url": "usa/nfl-2022-2023/washington-commanders-new-york-giants-6suFDDo5/"
    },
    {
        "date": "11/Dec",
        "team_1": "NYG",
        "score_1": 22,
        "score_2": 48,
        "team_2": "PHI",
        "game_url": "usa/nfl-2022-2023/new-york-giants-philadelphia-eagles-M5mLmH8a/"
    },
    {
        "date": "04/Dec",
        "team_1": "NYG",
        "score_1": 20,
        "score_2": 20,
        "team_2": "WSH",
        "game_url": "usa/nfl-2022-2023/new-york-giants-washington-commanders-WdA151OQ/"
    },
    {
        "date": "24/Nov",
        "team_1": "DAL",
        "score_1": 28,
        "score_2": 20,
        "team_2": "NYG",
        "game_url": "usa/nfl-2022-2023/dallas-cowboys-new-york-giants-CEOTs7Q2/"
    },
    {
        "date": "20/Nov",
        "team_1": "NYG",
        "score_1": 18,
        "score_2": 31,
        "team_2": "DET",
        "game_url": "usa/nfl-2022-2023/new-york-giants-detroit-lions-fJg9vYJA/"
    },
    {
        "date": "13/Nov",
        "team_1": "NYG",
        "score_1": 24,
        "score_2": 16,
        "team_2": "HOU",
        "game_url": "usa/nfl-2022-2023/new-york-giants-houston-texans-Eoc5Ag5U/"
    },
    {
        "date": "30/Oct",
        "team_1": "SEA",
        "score_1": 27,
        "score_2": 13,
        "team_2": "NYG",
        "game_url": "usa/nfl-2022-2023/seattle-seahawks-new-york-giants-E5gqnJMC/"
    },
    {
        "date": "23/Oct",
        "team_1": "JAX",
        "score_1": 17,
        "score_2": 23,
        "team_2": "NYG",
        "game_url": "usa/nfl-2022-2023/jacksonville-jaguars-new-york-giants-joVIZlXk/"
    },
    {
        "date": "16/Oct",
        "team_1": "NYG",
        "score_1": 24,
        "score_2": 20,
        "team_2": "BAL",
        "game_url": "usa/nfl-2022-2023/new-york-giants-baltimore-ravens-rHw7rPbN/"
    },
    {
        "date": "09/Oct",
        "team_1": "GB",
        "score_1": 22,
        "score_2": 27,
        "team_2": "NYG",
        "game_url": "usa/nfl-2022-2023/green-bay-packers-new-york-giants-hfB4HaLG/"
    },
    {
        "date": "02/Oct",
        "team_1": "NYG",
        "score_1": 20,
        "score_2": 12,
        "team_2": "CHI",
        "game_url": "usa/nfl-2022-2023/new-york-giants-chicago-bears-0tK6JHPf/"
    },
    {
        "date": "26/Sep",
        "team_1": "NYG",
        "score_1": 16,
        "score_2": 23,
        "team_2": "DAL",
        "game_url": "usa/nfl-2022-2023/new-york-giants-dallas-cowboys-MZWv5IA1/"
    },
    {
        "date": "18/Sep",
        "team_1": "NYG",
        "score_1": 19,
        "score_2": 16,
        "team_2": "CAR",
        "game_url": "usa/nfl-2022-2023/new-york-giants-carolina-panthers-AeNwajrB/"
    },
    {
        "date": "11/Sep",
        "team_1": "TEN",
        "score_1": 20,
        "score_2": 21,
        "team_2": "NYG",
        "game_url": "usa/nfl-2022-2023/tennessee-titans-new-york-giants-ll3bipOB/"
    },
    {
        "date": "28/Aug",
        "team_1": "NYJ",
        "score_1": 31,
        "score_2": 27,
        "team_2": "NYG",
        "game_url": "usa/nfl-2022-2023/new-york-jets-new-york-giants-n10IVPOl/"
    },
    {
        "date": "21/Aug",
        "team_1": "NYG",
        "score_1": 25,
        "score_2": 22,
        "team_2": "CIN",
        "game_url": "usa/nfl-2022-2023/new-york-giants-cincinnati-bengals-dzE8JbEd/"
    },
    {
        "date": "11/Aug",
        "team_1": "NE",
        "score_1": 21,
        "score_2": 23,
        "team_2": "NYG",
        "game_url": "usa/nfl-2022-2023/new-england-patriots-new-york-giants-h00SMzPJ/"
    },
    {
        "date": "09/Jan",
        "team_1": "NYG",
        "score_1": 7,
        "score_2": 22,
        "team_2": "WSH",
        "game_url": "usa/nfl-2021-2022/new-york-giants-washington-commanders-hAJYFOe0/"
    },
    {
        "date": "02/Jan",
        "team_1": "CHI",
        "score_1": 29,
        "score_2": 3,
        "team_2": "NYG",
        "game_url": "usa/nfl-2021-2022/chicago-bears-new-york-giants-OGnq57sr/"
    },
    {
        "date": "26/Dec",
        "team_1": "PHI",
        "score_1": 34,
        "score_2": 10,
        "team_2": "NYG",
        "game_url": "usa/nfl-2021-2022/philadelphia-eagles-new-york-giants-vi92dwaA/"
    },
    {
        "date": "19/Dec",
        "team_1": "NYG",
        "score_1": 6,
        "score_2": 21,
        "team_2": "DAL",
        "game_url": "usa/nfl-2021-2022/new-york-giants-dallas-cowboys-2oh8n2Vo/"
    },
    {
        "date": "12/Dec",
        "team_1": "LAC",
        "score_1": 37,
        "score_2": 21,
        "team_2": "NYG",
        "game_url": "usa/nfl-2021-2022/los-angeles-chargers-new-york-giants-2mPVVNN5/"
    },
    {
        "date": "05/Dec",
        "team_1": "MIA",
        "score_1": 20,
        "score_2": 9,
        "team_2": "NYG",
        "game_url": "usa/nfl-2021-2022/miami-dolphins-new-york-giants-llwsPFAL/"
    },
    {
        "date": "28/Nov",
        "team_1": "NYG",
        "score_1": 13,
        "score_2": 7,
        "team_2": "PHI",
        "game_url": "usa/nfl-2021-2022/new-york-giants-philadelphia-eagles-zuQfDIB9/"
    },
    {
        "date": "22/Nov",
        "team_1": "TB",
        "score_1": 30,
        "score_2": 10,
        "team_2": "NYG",
        "game_url": "usa/nfl-2021-2022/tampa-bay-buccaneers-new-york-giants-jZrVdcRS/"
    },
    {
        "date": "07/Nov",
        "team_1": "NYG",
        "score_1": 23,
        "score_2": 16,
        "team_2": "LV",
        "game_url": "usa/nfl-2021-2022/new-york-giants-las-vegas-raiders-WClH5X87/"
    },
    {
        "date": "01/Nov",
        "team_1": "KC",
        "score_1": 20,
        "score_2": 17,
        "team_2": "NYG",
        "game_url": "usa/nfl-2021-2022/kansas-city-chiefs-new-york-giants-noxQHw22/"
    },
    {
        "date": "24/Oct",
        "team_1": "NYG",
        "score_1": 25,
        "score_2": 3,
        "team_2": "CAR",
        "game_url": "usa/nfl-2021-2022/new-york-giants-carolina-panthers-t8az5u1a/"
    },
    {
        "date": "17/Oct",
        "team_1": "NYG",
        "score_1": 11,
        "score_2": 38,
        "team_2": "LAR",
        "game_url": "usa/nfl-2021-2022/new-york-giants-los-angeles-rams-zkLifOns/"
    },
    {
        "date": "10/Oct",
        "team_1": "DAL",
        "score_1": 44,
        "score_2": 20,
        "team_2": "NYG",
        "game_url": "usa/nfl-2021-2022/dallas-cowboys-new-york-giants-GplRw320/"
    },
    {
        "date": "03/Oct",
        "team_1": "NO",
        "score_1": 21,
        "score_2": 27,
        "team_2": "NYG",
        "game_url": "usa/nfl-2021-2022/new-orleans-saints-new-york-giants-KGTOZd5c/"
    },
    {
        "date": "26/Sep",
        "team_1": "NYG",
        "score_1": 14,
        "score_2": 17,
        "team_2": "ATL",
        "game_url": "usa/nfl-2021-2022/new-york-giants-atlanta-falcons-hSU88K6b/"
    },
    {
        "date": "16/Sep",
        "team_1": "WSH",
        "score_1": 30,
        "score_2": 29,
        "team_2": "NYG",
        "game_url": "usa/nfl-2021-2022/washington-commanders-new-york-giants-G8j0ALKl/"
    },
    {
        "date": "12/Sep",
        "team_1": "NYG",
        "score_1": 13,
        "score_2": 27,
        "team_2": "DEN",
        "game_url": "usa/nfl-2021-2022/new-york-giants-denver-broncos-6Z0QGNsL/"
    },
    {
        "date": "29/Aug",
        "team_1": "NYG",
        "score_1": 20,
        "score_2": 22,
        "team_2": "NE",
        "game_url": "usa/nfl-2021-2022/new-york-giants-new-england-patriots-WIZM078n/"
    },
    {
        "date": "22/Aug",
        "team_1": "CLE",
        "score_1": 17,
        "score_2": 13,
        "team_2": "NYG",
        "game_url": "usa/nfl-2021-2022/cleveland-browns-new-york-giants-bVlpo7i2/"
    },
    {
        "date": "14/Aug",
        "team_1": "NYG",
        "score_1": 7,
        "score_2": 12,
        "team_2": "NYJ",
        "game_url": "usa/nfl-2021-2022/new-york-giants-new-york-jets-nZ95Z9hj/"
    },
    {
        "date": "03/Jan",
        "team_1": "NYG",
        "score_1": 23,
        "score_2": 19,
        "team_2": "DAL",
        "game_url": "usa/nfl-2020-2021/new-york-giants-dallas-cowboys-vohmuzTQ/"
    },
    {
        "date": "27/Dec",
        "team_1": "BAL",
        "score_1": 27,
        "score_2": 13,
        "team_2": "NYG",
        "game_url": "usa/nfl-2020-2021/baltimore-ravens-new-york-giants-b7ACM6e2/"
    },
    {
        "date": "20/Dec",
        "team_1": "NYG",
        "score_1": 6,
        "score_2": 20,
        "team_2": "CLE",
        "game_url": "usa/nfl-2020-2021/new-york-giants-cleveland-browns-0Y1pXaDh/"
    },
    {
        "date": "13/Dec",
        "team_1": "NYG",
        "score_1": 7,
        "score_2": 26,
        "team_2": "ARI",
        "game_url": "usa/nfl-2020-2021/new-york-giants-arizona-cardinals-6cu7lMqJ/"
    },
    {
        "date": "06/Dec",
        "team_1": "SEA",
        "score_1": 12,
        "score_2": 17,
        "team_2": "NYG",
        "game_url": "usa/nfl-2020-2021/seattle-seahawks-new-york-giants-KMIVlVw2/"
    },
    {
        "date": "29/Nov",
        "team_1": "CIN",
        "score_1": 17,
        "score_2": 19,
        "team_2": "NYG",
        "game_url": "usa/nfl-2020-2021/cincinnati-bengals-new-york-giants-IFR2Qfep/"
    },
    {
        "date": "15/Nov",
        "team_1": "NYG",
        "score_1": 27,
        "score_2": 17,
        "team_2": "PHI",
        "game_url": "usa/nfl-2020-2021/new-york-giants-philadelphia-eagles-IJ7QSjLD/"
    },
    {
        "date": "08/Nov",
        "team_1": "WSH",
        "score_1": 20,
        "score_2": 23,
        "team_2": "NYG",
        "game_url": "usa/nfl-2020-2021/washington-commanders-new-york-giants-nBN27LX7/"
    },
    {
        "date": "02/Nov",
        "team_1": "NYG",
        "score_1": 23,
        "score_2": 25,
        "team_2": "TB",
        "game_url": "usa/nfl-2020-2021/new-york-giants-tampa-bay-buccaneers-6wX7Iot9/"
    },
    {
        "date": "22/Oct",
        "team_1": "PHI",
        "score_1": 22,
        "score_2": 21,
        "team_2": "NYG",
        "game_url": "usa/nfl-2020-2021/philadelphia-eagles-new-york-giants-xQJNkd65/"
    },
    {
        "date": "18/Oct",
        "team_1": "NYG",
        "score_1": 20,
        "score_2": 19,
        "team_2": "WSH",
        "game_url": "usa/nfl-2020-2021/new-york-giants-washington-commanders-j9etwJMa/"
    },
    {
        "date": "11/Oct",
        "team_1": "DAL",
        "score_1": 37,
        "score_2": 34,
        "team_2": "NYG",
        "game_url": "usa/nfl-2020-2021/dallas-cowboys-new-york-giants-txDINwNC/"
    },
    {
        "date": "04/Oct",
        "team_1": "LAR",
        "score_1": 17,
        "score_2": 9,
        "team_2": "NYG",
        "game_url": "usa/nfl-2020-2021/los-angeles-rams-new-york-giants-x4QrYWv3/"
    },
    {
        "date": "27/Sep",
        "team_1": "NYG",
        "score_1": 9,
        "score_2": 36,
        "team_2": "SF",
        "game_url": "usa/nfl-2020-2021/new-york-giants-san-francisco-49ers-jD7N9ddo/"
    },
    {
        "date": "20/Sep",
        "team_1": "CHI",
        "score_1": 17,
        "score_2": 13,
        "team_2": "NYG",
        "game_url": "usa/nfl-2020-2021/chicago-bears-new-york-giants-YFFt04DD/"
    },
    {
        "date": "14/Sep",
        "team_1": "NYG",
        "score_1": 16,
        "score_2": 26,
        "team_2": "PIT",
        "game_url": "usa/nfl-2020-2021/new-york-giants-pittsburgh-steelers-naDU26Tf/"
    },
    {
        "date": "29/Dec",
        "team_1": "NYG",
        "score_1": 17,
        "score_2": 34,
        "team_2": "PHI",
        "game_url": "usa/nfl-2019-2020/new-york-giants-philadelphia-eagles-vJuXTIzm/"
    },
    {
        "date": "22/Dec",
        "team_1": "WSH",
        "score_1": 35,
        "score_2": 41,
        "team_2": "NYG",
        "game_url": "usa/nfl-2019-2020/washington-commanders-new-york-giants-IZNR10if/"
    },
    {
        "date": "15/Dec",
        "team_1": "NYG",
        "score_1": 36,
        "score_2": 20,
        "team_2": "MIA",
        "game_url": "usa/nfl-2019-2020/new-york-giants-miami-dolphins-I7m88B89/"
    },
    {
        "date": "09/Dec",
        "team_1": "PHI",
        "score_1": 23,
        "score_2": 17,
        "team_2": "NYG",
        "game_url": "usa/nfl-2019-2020/philadelphia-eagles-new-york-giants-0WGshjOS/"
    },
    {
        "date": "01/Dec",
        "team_1": "NYG",
        "score_1": 13,
        "score_2": 31,
        "team_2": "GB",
        "game_url": "usa/nfl-2019-2020/new-york-giants-green-bay-packers-Oj9DVyBb/"
    },
    {
        "date": "24/Nov",
        "team_1": "CHI",
        "score_1": 19,
        "score_2": 14,
        "team_2": "NYG",
        "game_url": "usa/nfl-2019-2020/chicago-bears-new-york-giants-hUVWM7SQ/"
    },
    {
        "date": "10/Nov",
        "team_1": "NYJ",
        "score_1": 34,
        "score_2": 27,
        "team_2": "NYG",
        "game_url": "usa/nfl-2019-2020/new-york-jets-new-york-giants-hSbcGplc/"
    },
    {
        "date": "04/Nov",
        "team_1": "NYG",
        "score_1": 18,
        "score_2": 37,
        "team_2": "DAL",
        "game_url": "usa/nfl-2019-2020/new-york-giants-dallas-cowboys-hSxS05lA/"
    },
    {
        "date": "27/Oct",
        "team_1": "DET",
        "score_1": 31,
        "score_2": 26,
        "team_2": "NYG",
        "game_url": "usa/nfl-2019-2020/detroit-lions-new-york-giants-ABs9lyam/"
    },
    {
        "date": "20/Oct",
        "team_1": "NYG",
        "score_1": 21,
        "score_2": 27,
        "team_2": "ARI",
        "game_url": "usa/nfl-2019-2020/new-york-giants-arizona-cardinals-bDk9JGaD/"
    },
    {
        "date": "10/Oct",
        "team_1": "NE",
        "score_1": 35,
        "score_2": 14,
        "team_2": "NYG",
        "game_url": "usa/nfl-2019-2020/new-england-patriots-new-york-giants-WOIJC8nT/"
    },
    {
        "date": "06/Oct",
        "team_1": "NYG",
        "score_1": 10,
        "score_2": 28,
        "team_2": "MIN",
        "game_url": "usa/nfl-2019-2020/new-york-giants-minnesota-vikings-xxUjJh3o/"
    },
    {
        "date": "29/Sep",
        "team_1": "NYG",
        "score_1": 24,
        "score_2": 3,
        "team_2": "WSH",
        "game_url": "usa/nfl-2019-2020/new-york-giants-washington-commanders-8roJdEtP/"
    },
    {
        "date": "22/Sep",
        "team_1": "TB",
        "score_1": 31,
        "score_2": 32,
        "team_2": "NYG",
        "game_url": "usa/nfl-2019-2020/tampa-bay-buccaneers-new-york-giants-0EZHL6D8/"
    },
    {
        "date": "15/Sep",
        "team_1": "NYG",
        "score_1": 14,
        "score_2": 28,
        "team_2": "BUF",
        "game_url": "usa/nfl-2019-2020/new-york-giants-buffalo-bills-ENK0djpc/"
    },
    {
        "date": "08/Sep",
        "team_1": "DAL",
        "score_1": 35,
        "score_2": 17,
        "team_2": "NYG",
        "game_url": "usa/nfl-2019-2020/dallas-cowboys-new-york-giants-tdsKqD0i/"
    },
    {
        "date": "29/Aug",
        "team_1": "NE",
        "score_1": 29,
        "score_2": 31,
        "team_2": "NYG",
        "game_url": "usa/nfl-2019-2020/new-england-patriots-new-york-giants-A1EUemsf/"
    },
    {
        "date": "22/Aug",
        "team_1": "CIN",
        "score_1": 23,
        "score_2": 25,
        "team_2": "NYG",
        "game_url": "usa/nfl-2019-2020/cincinnati-bengals-new-york-giants-QeeDkCKK/"
    },
    {
        "date": "16/Aug",
        "team_1": "NYG",
        "score_1": 32,
        "score_2": 13,
        "team_2": "CHI",
        "game_url": "usa/nfl-2019-2020/new-york-giants-chicago-bears-fBPDUAre/"
    },
    {
        "date": "08/Aug",
        "team_1": "NYG",
        "score_1": 31,
        "score_2": 22,
        "team_2": "NYJ",
        "game_url": "usa/nfl-2019-2020/new-york-giants-new-york-jets-vJeeQei9/"
    },
    {
        "date": "30/Dec",
        "team_1": "NYG",
        "score_1": 35,
        "score_2": 36,
        "team_2": "DAL",
        "game_url": "usa/nfl-2018-2019/new-york-giants-dallas-cowboys-jDZLa33f/"
    },
    {
        "date": "23/Dec",
        "team_1": "IND",
        "score_1": 28,
        "score_2": 27,
        "team_2": "NYG",
        "game_url": "usa/nfl-2018-2019/indianapolis-colts-new-york-giants-0ruJA8fb/"
    },
    {
        "date": "16/Dec",
        "team_1": "NYG",
        "score_1": 0,
        "score_2": 17,
        "team_2": "TEN",
        "game_url": "usa/nfl-2018-2019/new-york-giants-tennessee-titans-pxpuaBen/"
    },
    {
        "date": "09/Dec",
        "team_1": "WSH",
        "score_1": 16,
        "score_2": 40,
        "team_2": "NYG",
        "game_url": "usa/nfl-2018-2019/washington-commanders-new-york-giants-W6qniNc8/"
    },
    {
        "date": "02/Dec",
        "team_1": "NYG",
        "score_1": 30,
        "score_2": 27,
        "team_2": "CHI",
        "game_url": "usa/nfl-2018-2019/new-york-giants-chicago-bears-QZ1MHM6k/"
    },
    {
        "date": "25/Nov",
        "team_1": "PHI",
        "score_1": 25,
        "score_2": 22,
        "team_2": "NYG",
        "game_url": "usa/nfl-2018-2019/philadelphia-eagles-new-york-giants-KYd8A5aM/"
    },
    {
        "date": "18/Nov",
        "team_1": "NYG",
        "score_1": 38,
        "score_2": 35,
        "team_2": "TB",
        "game_url": "usa/nfl-2018-2019/new-york-giants-tampa-bay-buccaneers-boRE0UVc/"
    },
    {
        "date": "12/Nov",
        "team_1": "SF",
        "score_1": 23,
        "score_2": 27,
        "team_2": "NYG",
        "game_url": "usa/nfl-2018-2019/san-francisco-49ers-new-york-giants-2aDt0cum/"
    },
    {
        "date": "28/Oct",
        "team_1": "NYG",
        "score_1": 13,
        "score_2": 20,
        "team_2": "WSH",
        "game_url": "usa/nfl-2018-2019/new-york-giants-washington-commanders-lIprsOHA/"
    },
    {
        "date": "22/Oct",
        "team_1": "ATL",
        "score_1": 23,
        "score_2": 20,
        "team_2": "NYG",
        "game_url": "usa/nfl-2018-2019/atlanta-falcons-new-york-giants-S2dZrpmb/"
    },
    {
        "date": "11/Oct",
        "team_1": "NYG",
        "score_1": 13,
        "score_2": 34,
        "team_2": "PHI",
        "game_url": "usa/nfl-2018-2019/new-york-giants-philadelphia-eagles-jqvy5U4g/"
    },
    {
        "date": "07/Oct",
        "team_1": "CAR",
        "score_1": 33,
        "score_2": 31,
        "team_2": "NYG",
        "game_url": "usa/nfl-2018-2019/carolina-panthers-new-york-giants-IFi5iBzf/"
    },
    {
        "date": "30/Sep",
        "team_1": "NYG",
        "score_1": 18,
        "score_2": 33,
        "team_2": "NO",
        "game_url": "usa/nfl-2018-2019/new-york-giants-new-orleans-saints-j5iQjvpq/"
    },
    {
        "date": "23/Sep",
        "team_1": "HOU",
        "score_1": 22,
        "score_2": 27,
        "team_2": "NYG",
        "game_url": "usa/nfl-2018-2019/houston-texans-new-york-giants-G6TqpZBT/"
    },
    {
        "date": "16/Sep",
        "team_1": "DAL",
        "score_1": 20,
        "score_2": 13,
        "team_2": "NYG",
        "game_url": "usa/nfl-2018-2019/dallas-cowboys-new-york-giants-IaZ5YyDH/"
    },
    {
        "date": "09/Sep",
        "team_1": "NYG",
        "score_1": 15,
        "score_2": 20,
        "team_2": "JAX",
        "game_url": "usa/nfl-2018-2019/new-york-giants-jacksonville-jaguars-tSshVB08/"
    },
    {
        "date": "30/Aug",
        "team_1": "NYG",
        "score_1": 12,
        "score_2": 17,
        "team_2": "NE",
        "game_url": "usa/nfl-2018-2019/new-york-giants-new-england-patriots-2BRCONX1/"
    },
    {
        "date": "24/Aug",
        "team_1": "NYJ",
        "score_1": 16,
        "score_2": 22,
        "team_2": "NYG",
        "game_url": "usa/nfl-2018-2019/new-york-jets-new-york-giants-jcibJSeM/"
    },
    {
        "date": "17/Aug",
        "team_1": "DET",
        "score_1": 17,
        "score_2": 30,
        "team_2": "NYG",
        "game_url": "usa/nfl-2018-2019/detroit-lions-new-york-giants-badeUXnQ/"
    },
    {
        "date": "09/Aug",
        "team_1": "NYG",
        "score_1": 10,
        "score_2": 20,
        "team_2": "CLE",
        "game_url": "usa/nfl-2018-2019/new-york-giants-cleveland-browns-fV557AuD/"
    },
    {
        "date": "31/Dec",
        "team_1": "NYG",
        "score_1": 18,
        "score_2": 10,
        "team_2": "WSH",
        "game_url": "usa/nfl-2017-2018/new-york-giants-washington-commanders-6iIDAuvI/"
    },
    {
        "date": "24/Dec",
        "team_1": "ARI",
        "score_1": 23,
        "score_2": 0,
        "team_2": "NYG",
        "game_url": "usa/nfl-2017-2018/arizona-cardinals-new-york-giants-IRTPBUIf/"
    },
    {
        "date": "17/Dec",
        "team_1": "NYG",
        "score_1": 29,
        "score_2": 34,
        "team_2": "PHI",
        "game_url": "usa/nfl-2017-2018/new-york-giants-philadelphia-eagles-ITYXhGCF/"
    },
    {
        "date": "10/Dec",
        "team_1": "NYG",
        "score_1": 10,
        "score_2": 30,
        "team_2": "DAL",
        "game_url": "usa/nfl-2017-2018/new-york-giants-dallas-cowboys-lz2rrabc/"
    },
    {
        "date": "03/Dec",
        "team_1": "LV",
        "score_1": 24,
        "score_2": 17,
        "team_2": "NYG",
        "game_url": "usa/nfl-2017-2018/las-vegas-raiders-new-york-giants-M1musbd6/"
    },
    {
        "date": "23/Nov",
        "team_1": "WSH",
        "score_1": 20,
        "score_2": 10,
        "team_2": "NYG",
        "game_url": "usa/nfl-2017-2018/washington-commanders-new-york-giants-YsCh22T7/"
    },
    {
        "date": "19/Nov",
        "team_1": "NYG",
        "score_1": 12,
        "score_2": 9,
        "team_2": "KC",
        "game_url": "usa/nfl-2017-2018/new-york-giants-kansas-city-chiefs-QJm4OhpA/"
    },
    {
        "date": "12/Nov",
        "team_1": "SF",
        "score_1": 31,
        "score_2": 21,
        "team_2": "NYG",
        "game_url": "usa/nfl-2017-2018/san-francisco-49ers-new-york-giants-Ea2UBF04/"
    },
    {
        "date": "05/Nov",
        "team_1": "NYG",
        "score_1": 17,
        "score_2": 51,
        "team_2": "LAR",
        "game_url": "usa/nfl-2017-2018/new-york-giants-los-angeles-rams-b9DDpw25/"
    },
    {
        "date": "22/Oct",
        "team_1": "NYG",
        "score_1": 7,
        "score_2": 24,
        "team_2": "SEA",
        "game_url": "usa/nfl-2017-2018/new-york-giants-seattle-seahawks-WKtOwVlL/"
    },
    {
        "date": "15/Oct",
        "team_1": "DEN",
        "score_1": 10,
        "score_2": 23,
        "team_2": "NYG",
        "game_url": "usa/nfl-2017-2018/denver-broncos-new-york-giants-ppGUTgLd/"
    },
    {
        "date": "08/Oct",
        "team_1": "NYG",
        "score_1": 22,
        "score_2": 27,
        "team_2": "LAC",
        "game_url": "usa/nfl-2017-2018/new-york-giants-los-angeles-chargers-zH9FKUQo/"
    },
    {
        "date": "01/Oct",
        "team_1": "TB",
        "score_1": 25,
        "score_2": 23,
        "team_2": "NYG",
        "game_url": "usa/nfl-2017-2018/tampa-bay-buccaneers-new-york-giants-2PW7OwSJ/"
    },
    {
        "date": "24/Sep",
        "team_1": "PHI",
        "score_1": 27,
        "score_2": 24,
        "team_2": "NYG",
        "game_url": "usa/nfl-2017-2018/philadelphia-eagles-new-york-giants-zyYic1TK/"
    },
    {
        "date": "18/Sep",
        "team_1": "NYG",
        "score_1": 10,
        "score_2": 24,
        "team_2": "DET",
        "game_url": "usa/nfl-2017-2018/new-york-giants-detroit-lions-6uhDo4U8/"
    },
    {
        "date": "10/Sep",
        "team_1": "DAL",
        "score_1": 19,
        "score_2": 3,
        "team_2": "NYG",
        "game_url": "usa/nfl-2017-2018/dallas-cowboys-new-york-giants-GYRfXD9b/"
    },
    {
        "date": "31/Aug",
        "team_1": "NE",
        "score_1": 38,
        "score_2": 40,
        "team_2": "NYG",
        "game_url": "usa/nfl-2017-2018/new-england-patriots-new-york-giants-Uoi5SS17/"
    },
    {
        "date": "26/Aug",
        "team_1": "NYG",
        "score_1": 32,
        "score_2": 31,
        "team_2": "NYJ",
        "game_url": "usa/nfl-2017-2018/new-york-giants-new-york-jets-ziGBM0ZG/"
    },
    {
        "date": "21/Aug",
        "team_1": "CLE",
        "score_1": 10,
        "score_2": 6,
        "team_2": "NYG",
        "game_url": "usa/nfl-2017-2018/cleveland-browns-new-york-giants-lfft7LZT/"
    },
    {
        "date": "11/Aug",
        "team_1": "NYG",
        "score_1": 12,
        "score_2": 20,
        "team_2": "PIT",
        "game_url": "usa/nfl-2017-2018/new-york-giants-pittsburgh-steelers-xIVZanMn/"
    },
    {
        "date": "08/Jan",
        "team_1": "GB",
        "score_1": 38,
        "score_2": 13,
        "team_2": "NYG",
        "game_url": "usa/nfl-2016-2017/green-bay-packers-new-york-giants-2m7axwZp/"
    },
    {
        "date": "01/Jan",
        "team_1": "WSH",
        "score_1": 10,
        "score_2": 19,
        "team_2": "NYG",
        "game_url": "usa/nfl-2016-2017/washington-commanders-new-york-giants-MRtRbsAr/"
    },
    {
        "date": "22/Dec",
        "team_1": "PHI",
        "score_1": 24,
        "score_2": 19,
        "team_2": "NYG",
        "game_url": "usa/nfl-2016-2017/philadelphia-eagles-new-york-giants-0GWZZxGp/"
    },
    {
        "date": "18/Dec",
        "team_1": "NYG",
        "score_1": 17,
        "score_2": 6,
        "team_2": "DET",
        "game_url": "usa/nfl-2016-2017/new-york-giants-detroit-lions-KtXkpNwh/"
    },
    {
        "date": "11/Dec",
        "team_1": "NYG",
        "score_1": 10,
        "score_2": 7,
        "team_2": "DAL",
        "game_url": "usa/nfl-2016-2017/new-york-giants-dallas-cowboys-8bevkCPJ/"
    },
    {
        "date": "04/Dec",
        "team_1": "PIT",
        "score_1": 24,
        "score_2": 14,
        "team_2": "NYG",
        "game_url": "usa/nfl-2016-2017/pittsburgh-steelers-new-york-giants-tAdONZQK/"
    },
    {
        "date": "27/Nov",
        "team_1": "CLE",
        "score_1": 13,
        "score_2": 27,
        "team_2": "NYG",
        "game_url": "usa/nfl-2016-2017/cleveland-browns-new-york-giants-K265B5yb/"
    },
    {
        "date": "20/Nov",
        "team_1": "NYG",
        "score_1": 22,
        "score_2": 16,
        "team_2": "CHI",
        "game_url": "usa/nfl-2016-2017/new-york-giants-chicago-bears-CdN8u5iU/"
    },
    {
        "date": "14/Nov",
        "team_1": "NYG",
        "score_1": 21,
        "score_2": 20,
        "team_2": "CIN",
        "game_url": "usa/nfl-2016-2017/new-york-giants-cincinnati-bengals-6PPMVTN5/"
    },
    {
        "date": "06/Nov",
        "team_1": "NYG",
        "score_1": 28,
        "score_2": 23,
        "team_2": "PHI",
        "game_url": "usa/nfl-2016-2017/new-york-giants-philadelphia-eagles-nZ3nsLAq/"
    },
    {
        "date": "23/Oct",
        "team_1": "LAR",
        "score_1": 10,
        "score_2": 17,
        "team_2": "NYG",
        "game_url": "usa/nfl-2016-2017/los-angeles-rams-new-york-giants-bipDBTKb/"
    },
    {
        "date": "16/Oct",
        "team_1": "NYG",
        "score_1": 27,
        "score_2": 23,
        "team_2": "BAL",
        "game_url": "usa/nfl-2016-2017/new-york-giants-baltimore-ravens-WtpYAdUm/"
    },
    {
        "date": "09/Oct",
        "team_1": "GB",
        "score_1": 23,
        "score_2": 16,
        "team_2": "NYG",
        "game_url": "usa/nfl-2016-2017/green-bay-packers-new-york-giants-AB71cw0l/"
    },
    {
        "date": "03/Oct",
        "team_1": "MIN",
        "score_1": 24,
        "score_2": 10,
        "team_2": "NYG",
        "game_url": "usa/nfl-2016-2017/minnesota-vikings-new-york-giants-Q5lpi2wF/"
    },
    {
        "date": "25/Sep",
        "team_1": "NYG",
        "score_1": 27,
        "score_2": 29,
        "team_2": "WSH",
        "game_url": "usa/nfl-2016-2017/new-york-giants-washington-commanders-t24ngiUj/"
    },
    {
        "date": "18/Sep",
        "team_1": "NYG",
        "score_1": 16,
        "score_2": 13,
        "team_2": "NO",
        "game_url": "usa/nfl-2016-2017/new-york-giants-new-orleans-saints-jy4h8QwQ/"
    },
    {
        "date": "11/Sep",
        "team_1": "DAL",
        "score_1": 19,
        "score_2": 20,
        "team_2": "NYG",
        "game_url": "usa/nfl-2016-2017/dallas-cowboys-new-york-giants-U3MelsBK/"
    },
    {
        "date": "01/Sep",
        "team_1": "NYG",
        "score_1": 17,
        "score_2": 9,
        "team_2": "NE",
        "game_url": "usa/nfl-2016-2017/new-york-giants-new-england-patriots-C6bWO5QB/"
    },
    {
        "date": "27/Aug",
        "team_1": "NYJ",
        "score_1": 20,
        "score_2": 21,
        "team_2": "NYG",
        "game_url": "usa/nfl-2016-2017/new-york-jets-new-york-giants-GjmYFAss/"
    },
    {
        "date": "20/Aug",
        "team_1": "BUF",
        "score_1": 21,
        "score_2": 0,
        "team_2": "NYG",
        "game_url": "usa/nfl-2016-2017/buffalo-bills-new-york-giants-OvTK8gzE/"
    },
    {
        "date": "12/Aug",
        "team_1": "NYG",
        "score_1": 10,
        "score_2": 27,
        "team_2": "MIA",
        "game_url": "usa/nfl-2016-2017/new-york-giants-miami-dolphins-jg9qvrVM/"
    },
    {
        "date": "03/Jan",
        "team_1": "NYG",
        "score_1": 30,
        "score_2": 35,
        "team_2": "PHI",
        "game_url": "usa/nfl-2015-2016/new-york-giants-philadelphia-eagles-zZ6okjuo/"
    },
    {
        "date": "27/Dec",
        "team_1": "MIN",
        "score_1": 49,
        "score_2": 17,
        "team_2": "NYG",
        "game_url": "usa/nfl-2015-2016/minnesota-vikings-new-york-giants-xKv0s2s7/"
    },
    {
        "date": "20/Dec",
        "team_1": "NYG",
        "score_1": 35,
        "score_2": 38,
        "team_2": "CAR",
        "game_url": "usa/nfl-2015-2016/new-york-giants-carolina-panthers-2PSVwTzF/"
    },
    {
        "date": "14/Dec",
        "team_1": "MIA",
        "score_1": 24,
        "score_2": 31,
        "team_2": "NYG",
        "game_url": "usa/nfl-2015-2016/miami-dolphins-new-york-giants-bVp4PTLL/"
    },
    {
        "date": "06/Dec",
        "team_1": "NYG",
        "score_1": 20,
        "score_2": 23,
        "team_2": "NYJ",
        "game_url": "usa/nfl-2015-2016/new-york-giants-new-york-jets-80j1zZCP/"
    },
    {
        "date": "29/Nov",
        "team_1": "WSH",
        "score_1": 20,
        "score_2": 14,
        "team_2": "NYG",
        "game_url": "usa/nfl-2015-2016/washington-commanders-new-york-giants-fN7u0hyD/"
    },
    {
        "date": "15/Nov",
        "team_1": "NYG",
        "score_1": 26,
        "score_2": 27,
        "team_2": "NE",
        "game_url": "usa/nfl-2015-2016/new-york-giants-new-england-patriots-2T2Jblfi/"
    },
    {
        "date": "08/Nov",
        "team_1": "TB",
        "score_1": 18,
        "score_2": 32,
        "team_2": "NYG",
        "game_url": "usa/nfl-2015-2016/tampa-bay-buccaneers-new-york-giants-tblRTTfH/"
    },
    {
        "date": "01/Nov",
        "team_1": "NO",
        "score_1": 52,
        "score_2": 49,
        "team_2": "NYG",
        "game_url": "usa/nfl-2015-2016/new-orleans-saints-new-york-giants-Wn1ewsSD/"
    },
    {
        "date": "25/Oct",
        "team_1": "NYG",
        "score_1": 27,
        "score_2": 20,
        "team_2": "DAL",
        "game_url": "usa/nfl-2015-2016/new-york-giants-dallas-cowboys-WQPKQ3r8/"
    },
    {
        "date": "19/Oct",
        "team_1": "PHI",
        "score_1": 27,
        "score_2": 7,
        "team_2": "NYG",
        "game_url": "usa/nfl-2015-2016/philadelphia-eagles-new-york-giants-nL6sErqd/"
    },
    {
        "date": "11/Oct",
        "team_1": "NYG",
        "score_1": 30,
        "score_2": 27,
        "team_2": "SF",
        "game_url": "usa/nfl-2015-2016/new-york-giants-san-francisco-49ers-CvEG9TiA/"
    },
    {
        "date": "04/Oct",
        "team_1": "BUF",
        "score_1": 10,
        "score_2": 24,
        "team_2": "NYG",
        "game_url": "usa/nfl-2015-2016/buffalo-bills-new-york-giants-IqkuuInJ/"
    },
    {
        "date": "24/Sep",
        "team_1": "NYG",
        "score_1": 32,
        "score_2": 21,
        "team_2": "WSH",
        "game_url": "usa/nfl-2015-2016/new-york-giants-washington-commanders-Wptavod8/"
    },
    {
        "date": "20/Sep",
        "team_1": "NYG",
        "score_1": 20,
        "score_2": 24,
        "team_2": "ATL",
        "game_url": "usa/nfl-2015-2016/new-york-giants-atlanta-falcons-INHVxYK3/"
    },
    {
        "date": "13/Sep",
        "team_1": "DAL",
        "score_1": 27,
        "score_2": 26,
        "team_2": "NYG",
        "game_url": "usa/nfl-2015-2016/dallas-cowboys-new-york-giants-lUlpRzMi/"
    },
    {
        "date": "03/Sep",
        "team_1": "NE",
        "score_1": 9,
        "score_2": 12,
        "team_2": "NYG",
        "game_url": "usa/nfl-2015-2016/new-england-patriots-new-york-giants-zsV70Ad6/"
    },
    {
        "date": "29/Aug",
        "team_1": "NYG",
        "score_1": 18,
        "score_2": 28,
        "team_2": "NYJ",
        "game_url": "usa/nfl-2015-2016/new-york-giants-new-york-jets-pz5knKyd/"
    },
    {
        "date": "22/Aug",
        "team_1": "NYG",
        "score_1": 22,
        "score_2": 12,
        "team_2": "JAX",
        "game_url": "usa/nfl-2015-2016/new-york-giants-jacksonville-jaguars-MNKysPaG/"
    },
    {
        "date": "14/Aug",
        "team_1": "CIN",
        "score_1": 23,
        "score_2": 10,
        "team_2": "NYG",
        "game_url": "usa/nfl-2015-2016/cincinnati-bengals-new-york-giants-Eg3RQC9I/"
    },
    {
        "date": "28/Dec",
        "team_1": "NYG",
        "score_1": 26,
        "score_2": 34,
        "team_2": "PHI",
        "game_url": "usa/nfl-2014-2015/new-york-giants-philadelphia-eagles-S8RsADXe/"
    },
    {
        "date": "21/Dec",
        "team_1": "LAR",
        "score_1": 27,
        "score_2": 37,
        "team_2": "NYG",
        "game_url": "usa/nfl-2014-2015/los-angeles-rams-new-york-giants-zZl7K6kn/"
    },
    {
        "date": "14/Dec",
        "team_1": "NYG",
        "score_1": 24,
        "score_2": 13,
        "team_2": "WSH",
        "game_url": "usa/nfl-2014-2015/new-york-giants-washington-commanders-hzT2hl6g/"
    },
    {
        "date": "07/Dec",
        "team_1": "TEN",
        "score_1": 7,
        "score_2": 36,
        "team_2": "NYG",
        "game_url": "usa/nfl-2014-2015/tennessee-titans-new-york-giants-GIRFOIod/"
    },
    {
        "date": "30/Nov",
        "team_1": "JAX",
        "score_1": 25,
        "score_2": 24,
        "team_2": "NYG",
        "game_url": "usa/nfl-2014-2015/jacksonville-jaguars-new-york-giants-4IWZXMO9/"
    },
    {
        "date": "23/Nov",
        "team_1": "NYG",
        "score_1": 28,
        "score_2": 31,
        "team_2": "DAL",
        "game_url": "usa/nfl-2014-2015/new-york-giants-dallas-cowboys-tGTsvwUo/"
    },
    {
        "date": "16/Nov",
        "team_1": "NYG",
        "score_1": 10,
        "score_2": 16,
        "team_2": "SF",
        "game_url": "usa/nfl-2014-2015/new-york-giants-san-francisco-49ers-ERURC0Vn/"
    },
    {
        "date": "09/Nov",
        "team_1": "SEA",
        "score_1": 38,
        "score_2": 17,
        "team_2": "NYG",
        "game_url": "usa/nfl-2014-2015/seattle-seahawks-new-york-giants-61myfnP7/"
    },
    {
        "date": "03/Nov",
        "team_1": "NYG",
        "score_1": 24,
        "score_2": 40,
        "team_2": "IND",
        "game_url": "usa/nfl-2014-2015/new-york-giants-indianapolis-colts-KW9fs9u2/"
    },
    {
        "date": "19/Oct",
        "team_1": "DAL",
        "score_1": 31,
        "score_2": 21,
        "team_2": "NYG",
        "game_url": "usa/nfl-2014-2015/dallas-cowboys-new-york-giants-vuDVL1DO/"
    },
    {
        "date": "12/Oct",
        "team_1": "PHI",
        "score_1": 27,
        "score_2": 0,
        "team_2": "NYG",
        "game_url": "usa/nfl-2014-2015/philadelphia-eagles-new-york-giants-rP1XC6Ug/"
    },
    {
        "date": "05/Oct",
        "team_1": "NYG",
        "score_1": 30,
        "score_2": 20,
        "team_2": "ATL",
        "game_url": "usa/nfl-2014-2015/new-york-giants-atlanta-falcons-UoeM21kk/"
    },
    {
        "date": "25/Sep",
        "team_1": "WSH",
        "score_1": 14,
        "score_2": 45,
        "team_2": "NYG",
        "game_url": "usa/nfl-2014-2015/washington-commanders-new-york-giants-zqtQegx5/"
    },
    {
        "date": "21/Sep",
        "team_1": "NYG",
        "score_1": 30,
        "score_2": 17,
        "team_2": "HOU",
        "game_url": "usa/nfl-2014-2015/new-york-giants-houston-texans-Auc2tExI/"
    },
    {
        "date": "14/Sep",
        "team_1": "NYG",
        "score_1": 14,
        "score_2": 25,
        "team_2": "ARI",
        "game_url": "usa/nfl-2014-2015/new-york-giants-arizona-cardinals-KYWqSNH7/"
    },
    {
        "date": "08/Sep",
        "team_1": "DET",
        "score_1": 35,
        "score_2": 14,
        "team_2": "NYG",
        "game_url": "usa/nfl-2014-2015/detroit-lions-new-york-giants-nLdpvUA2/"
    },
    {
        "date": "28/Aug",
        "team_1": "NYG",
        "score_1": 16,
        "score_2": 13,
        "team_2": "NE",
        "game_url": "usa/nfl-2014-2015/new-york-giants-new-england-patriots-St9AdWRM/"
    },
    {
        "date": "22/Aug",
        "team_1": "NYJ",
        "score_1": 24,
        "score_2": 35,
        "team_2": "NYG",
        "game_url": "usa/nfl-2014-2015/new-york-jets-new-york-giants-46Wg0gB0/"
    },
    {
        "date": "16/Aug",
        "team_1": "IND",
        "score_1": 26,
        "score_2": 27,
        "team_2": "NYG",
        "game_url": "usa/nfl-2014-2015/indianapolis-colts-new-york-giants-G8WsYzS7/"
    },
    {
        "date": "09/Aug",
        "team_1": "NYG",
        "score_1": 20,
        "score_2": 16,
        "team_2": "PIT",
        "game_url": "usa/nfl-2014-2015/new-york-giants-pittsburgh-steelers-nTvRyJSr/"
    },
    {
        "date": "03/Aug",
        "team_1": "BUF",
        "score_1": 13,
        "score_2": 17,
        "team_2": "NYG",
        "game_url": "usa/nfl-2014-2015/buffalo-bills-new-york-giants-n9rAqAUi/"
    },
    {
        "date": "29/Dec",
        "team_1": "NYG",
        "score_1": 20,
        "score_2": 6,
        "team_2": "WSH",
        "game_url": "usa/nfl-2013-2014/new-york-giants-washington-commanders-0YaQLmeM/"
    },
    {
        "date": "22/Dec",
        "team_1": "DET",
        "score_1": 20,
        "score_2": 23,
        "team_2": "NYG",
        "game_url": "usa/nfl-2013-2014/detroit-lions-new-york-giants-fV95QBti/"
    },
    {
        "date": "15/Dec",
        "team_1": "NYG",
        "score_1": 0,
        "score_2": 23,
        "team_2": "SEA",
        "game_url": "usa/nfl-2013-2014/new-york-giants-seattle-seahawks-YNZXb5WB/"
    },
    {
        "date": "08/Dec",
        "team_1": "LAC",
        "score_1": 37,
        "score_2": 14,
        "team_2": "NYG",
        "game_url": "usa/nfl-2013-2014/los-angeles-chargers-new-york-giants-KhLqLemE/"
    },
    {
        "date": "01/Dec",
        "team_1": "WSH",
        "score_1": 17,
        "score_2": 24,
        "team_2": "NYG",
        "game_url": "usa/nfl-2013-2014/washington-commanders-new-york-giants-IgpBmHRr/"
    },
    {
        "date": "24/Nov",
        "team_1": "NYG",
        "score_1": 21,
        "score_2": 24,
        "team_2": "DAL",
        "game_url": "usa/nfl-2013-2014/new-york-giants-dallas-cowboys-Wx0bLbrj/"
    },
    {
        "date": "17/Nov",
        "team_1": "NYG",
        "score_1": 27,
        "score_2": 13,
        "team_2": "GB",
        "game_url": "usa/nfl-2013-2014/new-york-giants-green-bay-packers-MoFvS9a5/"
    },
    {
        "date": "10/Nov",
        "team_1": "NYG",
        "score_1": 24,
        "score_2": 20,
        "team_2": "LV",
        "game_url": "usa/nfl-2013-2014/new-york-giants-las-vegas-raiders-rcLrAyvK/"
    },
    {
        "date": "27/Oct",
        "team_1": "PHI",
        "score_1": 7,
        "score_2": 15,
        "team_2": "NYG",
        "game_url": "usa/nfl-2013-2014/philadelphia-eagles-new-york-giants-2o8cbJNA/"
    },
    {
        "date": "21/Oct",
        "team_1": "NYG",
        "score_1": 23,
        "score_2": 7,
        "team_2": "MIN",
        "game_url": "usa/nfl-2013-2014/new-york-giants-minnesota-vikings-CdFp1Lwh/"
    },
    {
        "date": "10/Oct",
        "team_1": "CHI",
        "score_1": 27,
        "score_2": 21,
        "team_2": "NYG",
        "game_url": "usa/nfl-2013-2014/chicago-bears-new-york-giants-WryjOots/"
    },
    {
        "date": "06/Oct",
        "team_1": "NYG",
        "score_1": 21,
        "score_2": 36,
        "team_2": "PHI",
        "game_url": "usa/nfl-2013-2014/new-york-giants-philadelphia-eagles-bibrSfsF/"
    },
    {
        "date": "29/Sep",
        "team_1": "KC",
        "score_1": 31,
        "score_2": 7,
        "team_2": "NYG",
        "game_url": "usa/nfl-2013-2014/kansas-city-chiefs-new-york-giants-O0v7gzyj/"
    },
    {
        "date": "22/Sep",
        "team_1": "CAR",
        "score_1": 38,
        "score_2": 0,
        "team_2": "NYG",
        "game_url": "usa/nfl-2013-2014/carolina-panthers-new-york-giants-GEwgTwNp/"
    },
    {
        "date": "15/Sep",
        "team_1": "NYG",
        "score_1": 23,
        "score_2": 41,
        "team_2": "DEN",
        "game_url": "usa/nfl-2013-2014/new-york-giants-denver-broncos-SWJ4kUwm/"
    },
    {
        "date": "08/Sep",
        "team_1": "DAL",
        "score_1": 36,
        "score_2": 31,
        "team_2": "NYG",
        "game_url": "usa/nfl-2013-2014/dallas-cowboys-new-york-giants-K2QjqB17/"
    },
    {
        "date": "29/Aug",
        "team_1": "NE",
        "score_1": 28,
        "score_2": 20,
        "team_2": "NYG",
        "game_url": "usa/nfl-2013-2014/new-england-patriots-new-york-giants-bcyxF8ja/"
    },
    {
        "date": "24/Aug",
        "team_1": "NYG",
        "score_1": 21,
        "score_2": 24,
        "team_2": "NYJ",
        "game_url": "usa/nfl-2013-2014/new-york-giants-new-york-jets-4zfXpUyJ/"
    },
    {
        "date": "18/Aug",
        "team_1": "NYG",
        "score_1": 12,
        "score_2": 20,
        "team_2": "IND",
        "game_url": "usa/nfl-2013-2014/new-york-giants-indianapolis-colts-ILWv80wF/"
    },
    {
        "date": "10/Aug",
        "team_1": "PIT",
        "score_1": 13,
        "score_2": 18,
        "team_2": "NYG",
        "game_url": "usa/nfl-2013-2014/pittsburgh-steelers-new-york-giants-QBJwu29S/"
    },
    {
        "date": "30/Dec",
        "team_1": "NYG",
        "score_1": 42,
        "score_2": 7,
        "team_2": "PHI",
        "game_url": "usa/nfl-2012-2013/new-york-giants-philadelphia-eagles-YuXKS13f/"
    },
    {
        "date": "23/Dec",
        "team_1": "BAL",
        "score_1": 33,
        "score_2": 14,
        "team_2": "NYG",
        "game_url": "usa/nfl-2012-2013/baltimore-ravens-new-york-giants-n1IWCFE8/"
    },
    {
        "date": "16/Dec",
        "team_1": "ATL",
        "score_1": 34,
        "score_2": 0,
        "team_2": "NYG",
        "game_url": "usa/nfl-2012-2013/atlanta-falcons-new-york-giants-8I3n6ku3/"
    },
    {
        "date": "09/Dec",
        "team_1": "NYG",
        "score_1": 52,
        "score_2": 27,
        "team_2": "NO",
        "game_url": "usa/nfl-2012-2013/new-york-giants-new-orleans-saints-KdNip8Iq/"
    },
    {
        "date": "03/Dec",
        "team_1": "WSH",
        "score_1": 17,
        "score_2": 16,
        "team_2": "NYG",
        "game_url": "usa/nfl-2012-2013/washington-commanders-new-york-giants-KxRzhaKh/"
    },
    {
        "date": "25/Nov",
        "team_1": "NYG",
        "score_1": 38,
        "score_2": 10,
        "team_2": "GB",
        "game_url": "usa/nfl-2012-2013/new-york-giants-green-bay-packers-CYWUbhFn/"
    },
    {
        "date": "11/Nov",
        "team_1": "CIN",
        "score_1": 31,
        "score_2": 13,
        "team_2": "NYG",
        "game_url": "usa/nfl-2012-2013/cincinnati-bengals-new-york-giants-YNDElTu4/"
    },
    {
        "date": "04/Nov",
        "team_1": "NYG",
        "score_1": 20,
        "score_2": 24,
        "team_2": "PIT",
        "game_url": "usa/nfl-2012-2013/new-york-giants-pittsburgh-steelers-v39jpElI/"
    },
    {
        "date": "28/Oct",
        "team_1": "DAL",
        "score_1": 24,
        "score_2": 29,
        "team_2": "NYG",
        "game_url": "usa/nfl-2012-2013/dallas-cowboys-new-york-giants-z59CnHeJ/"
    },
    {
        "date": "21/Oct",
        "team_1": "NYG",
        "score_1": 27,
        "score_2": 23,
        "team_2": "WSH",
        "game_url": "usa/nfl-2012-2013/new-york-giants-washington-commanders-S8NFqmcE/"
    },
    {
        "date": "14/Oct",
        "team_1": "SF",
        "score_1": 3,
        "score_2": 26,
        "team_2": "NYG",
        "game_url": "usa/nfl-2012-2013/san-francisco-49ers-new-york-giants-IHvMuJvq/"
    },
    {
        "date": "07/Oct",
        "team_1": "NYG",
        "score_1": 41,
        "score_2": 27,
        "team_2": "CLE",
        "game_url": "usa/nfl-2012-2013/new-york-giants-cleveland-browns-jTu6Ettp/"
    },
    {
        "date": "30/Sep",
        "team_1": "PHI",
        "score_1": 19,
        "score_2": 17,
        "team_2": "NYG",
        "game_url": "usa/nfl-2012-2013/philadelphia-eagles-new-york-giants-UcaQRdF7/"
    },
    {
        "date": "20/Sep",
        "team_1": "CAR",
        "score_1": 7,
        "score_2": 36,
        "team_2": "NYG",
        "game_url": "usa/nfl-2012-2013/carolina-panthers-new-york-giants-WEeeI05o/"
    },
    {
        "date": "16/Sep",
        "team_1": "NYG",
        "score_1": 41,
        "score_2": 34,
        "team_2": "TB",
        "game_url": "usa/nfl-2012-2013/new-york-giants-tampa-bay-buccaneers-YLzsixnC/"
    },
    {
        "date": "05/Sep",
        "team_1": "NYG",
        "score_1": 17,
        "score_2": 24,
        "team_2": "DAL",
        "game_url": "usa/nfl-2012-2013/new-york-giants-dallas-cowboys-rDFrrs3s/"
    },
    {
        "date": "29/Aug",
        "team_1": "NYG",
        "score_1": 6,
        "score_2": 3,
        "team_2": "NE",
        "game_url": "usa/nfl-2012-2013/new-york-giants-new-england-patriots-nslmZj8K/"
    },
    {
        "date": "24/Aug",
        "team_1": "NYG",
        "score_1": 17,
        "score_2": 20,
        "team_2": "CHI",
        "game_url": "usa/nfl-2012-2013/new-york-giants-chicago-bears-fTQFYJH9/"
    },
    {
        "date": "18/Aug",
        "team_1": "NYJ",
        "score_1": 3,
        "score_2": 26,
        "team_2": "NYG",
        "game_url": "usa/nfl-2012-2013/new-york-jets-new-york-giants-hnPB4u3T/"
    },
    {
        "date": "10/Aug",
        "team_1": "JAX",
        "score_1": 32,
        "score_2": 31,
        "team_2": "NYG",
        "game_url": "usa/nfl-2012-2013/jacksonville-jaguars-new-york-giants-pdA9dQ4h/"
    },
    {
        "date": "05/Feb",
        "team_1": "NYG",
        "score_1": 21,
        "score_2": 17,
        "team_2": "NE",
        "game_url": "usa/nfl-2011-2012/new-york-giants-new-england-patriots-ninqNXmU/"
    },
    {
        "date": "22/Jan",
        "team_1": "SF",
        "score_1": 17,
        "score_2": 20,
        "team_2": "NYG",
        "game_url": "usa/nfl-2011-2012/san-francisco-49ers-new-york-giants-67e7Hw21/"
    },
    {
        "date": "15/Jan",
        "team_1": "GB",
        "score_1": 20,
        "score_2": 37,
        "team_2": "NYG",
        "game_url": "usa/nfl-2011-2012/green-bay-packers-new-york-giants-pM46Q0b1/"
    },
    {
        "date": "08/Jan",
        "team_1": "NYG",
        "score_1": 24,
        "score_2": 2,
        "team_2": "ATL",
        "game_url": "usa/nfl-2011-2012/new-york-giants-atlanta-falcons-2w9oE0nn/"
    },
    {
        "date": "01/Jan",
        "team_1": "NYG",
        "score_1": 31,
        "score_2": 14,
        "team_2": "DAL",
        "game_url": "usa/nfl-2011-2012/new-york-giants-dallas-cowboys-OKDOMmBe/"
    },
    {
        "date": "24/Dec",
        "team_1": "NYJ",
        "score_1": 14,
        "score_2": 29,
        "team_2": "NYG",
        "game_url": "usa/nfl-2011-2012/new-york-jets-new-york-giants-URqrkEnt/"
    },
    {
        "date": "18/Dec",
        "team_1": "NYG",
        "score_1": 10,
        "score_2": 23,
        "team_2": "WSH",
        "game_url": "usa/nfl-2011-2012/new-york-giants-washington-commanders-EgpNScQJ/"
    },
    {
        "date": "11/Dec",
        "team_1": "DAL",
        "score_1": 34,
        "score_2": 37,
        "team_2": "NYG",
        "game_url": "usa/nfl-2011-2012/dallas-cowboys-new-york-giants-I74O7dlf/"
    },
    {
        "date": "04/Dec",
        "team_1": "NYG",
        "score_1": 35,
        "score_2": 38,
        "team_2": "GB",
        "game_url": "usa/nfl-2011-2012/new-york-giants-green-bay-packers-G2tjgQrj/"
    },
    {
        "date": "28/Nov",
        "team_1": "NO",
        "score_1": 49,
        "score_2": 24,
        "team_2": "NYG",
        "game_url": "usa/nfl-2011-2012/new-orleans-saints-new-york-giants-YipHnkMG/"
    },
    {
        "date": "20/Nov",
        "team_1": "NYG",
        "score_1": 10,
        "score_2": 17,
        "team_2": "PHI",
        "game_url": "usa/nfl-2011-2012/new-york-giants-philadelphia-eagles-nsavKWxO/"
    },
    {
        "date": "13/Nov",
        "team_1": "SF",
        "score_1": 27,
        "score_2": 20,
        "team_2": "NYG",
        "game_url": "usa/nfl-2011-2012/san-francisco-49ers-new-york-giants-EJy1T3PQ/"
    },
    {
        "date": "06/Nov",
        "team_1": "NE",
        "score_1": 20,
        "score_2": 24,
        "team_2": "NYG",
        "game_url": "usa/nfl-2011-2012/new-england-patriots-new-york-giants-650cDx8q/"
    },
    {
        "date": "30/Oct",
        "team_1": "NYG",
        "score_1": 20,
        "score_2": 17,
        "team_2": "MIA",
        "game_url": "usa/nfl-2011-2012/new-york-giants-miami-dolphins-dMDF6Aug/"
    },
    {
        "date": "16/Oct",
        "team_1": "NYG",
        "score_1": 27,
        "score_2": 24,
        "team_2": "BUF",
        "game_url": "usa/nfl-2011-2012/new-york-giants-buffalo-bills-bF58mGlK/"
    },
    {
        "date": "09/Oct",
        "team_1": "NYG",
        "score_1": 25,
        "score_2": 36,
        "team_2": "SEA",
        "game_url": "usa/nfl-2011-2012/new-york-giants-seattle-seahawks-U7saGHDr/"
    },
    {
        "date": "02/Oct",
        "team_1": "ARI",
        "score_1": 27,
        "score_2": 31,
        "team_2": "NYG",
        "game_url": "usa/nfl-2011-2012/arizona-cardinals-new-york-giants-phqiI4qT/"
    },
    {
        "date": "25/Sep",
        "team_1": "PHI",
        "score_1": 16,
        "score_2": 29,
        "team_2": "NYG",
        "game_url": "usa/nfl-2011-2012/philadelphia-eagles-new-york-giants-86noDNkg/"
    },
    {
        "date": "19/Sep",
        "team_1": "NYG",
        "score_1": 28,
        "score_2": 16,
        "team_2": "LAR",
        "game_url": "usa/nfl-2011-2012/new-york-giants-los-angeles-rams-nibxFqLt/"
    },
    {
        "date": "11/Sep",
        "team_1": "WSH",
        "score_1": 28,
        "score_2": 14,
        "team_2": "NYG",
        "game_url": "usa/nfl-2011-2012/washington-commanders-new-york-giants-nHsK6eN2/"
    },
    {
        "date": "01/Sep",
        "team_1": "NE",
        "score_1": 17,
        "score_2": 18,
        "team_2": "NYG",
        "game_url": "usa/nfl-2011-2012/new-england-patriots-new-york-giants-OYSEeO1U/"
    },
    {
        "date": "29/Aug",
        "team_1": "NYG",
        "score_1": 3,
        "score_2": 17,
        "team_2": "NYJ",
        "game_url": "usa/nfl-2011-2012/new-york-giants-new-york-jets-lCGY2l3t/"
    },
    {
        "date": "22/Aug",
        "team_1": "NYG",
        "score_1": 41,
        "score_2": 13,
        "team_2": "CHI",
        "game_url": "usa/nfl-2011-2012/new-york-giants-chicago-bears-b3B8xyOS/"
    },
    {
        "date": "13/Aug",
        "team_1": "CAR",
        "score_1": 20,
        "score_2": 10,
        "team_2": "NYG",
        "game_url": "usa/nfl-2011-2012/carolina-panthers-new-york-giants-nydLPtCf/"
    },
    {
        "date": "02/Jan",
        "team_1": "WSH",
        "score_1": 14,
        "score_2": 17,
        "team_2": "NYG",
        "game_url": "usa/nfl-2010-2011/washington-commanders-new-york-giants-CpQnvbT2/"
    },
    {
        "date": "26/Dec",
        "team_1": "GB",
        "score_1": 45,
        "score_2": 17,
        "team_2": "NYG",
        "game_url": "usa/nfl-2010-2011/green-bay-packers-new-york-giants-KKIJ9JEM/"
    },
    {
        "date": "19/Dec",
        "team_1": "NYG",
        "score_1": 31,
        "score_2": 38,
        "team_2": "PHI",
        "game_url": "usa/nfl-2010-2011/new-york-giants-philadelphia-eagles-I9NOaBfm/"
    },
    {
        "date": "13/Dec",
        "team_1": "MIN",
        "score_1": 3,
        "score_2": 21,
        "team_2": "NYG",
        "game_url": "usa/nfl-2010-2011/minnesota-vikings-new-york-giants-YkDmXhBf/"
    },
    {
        "date": "05/Dec",
        "team_1": "NYG",
        "score_1": 31,
        "score_2": 7,
        "team_2": "WSH",
        "game_url": "usa/nfl-2010-2011/new-york-giants-washington-commanders-GrOHtQcc/"
    },
    {
        "date": "28/Nov",
        "team_1": "NYG",
        "score_1": 24,
        "score_2": 20,
        "team_2": "JAX",
        "game_url": "usa/nfl-2010-2011/new-york-giants-jacksonville-jaguars-U9pnTI2B/"
    },
    {
        "date": "21/Nov",
        "team_1": "PHI",
        "score_1": 27,
        "score_2": 17,
        "team_2": "NYG",
        "game_url": "usa/nfl-2010-2011/philadelphia-eagles-new-york-giants-6qVqHL3a/"
    },
    {
        "date": "14/Nov",
        "team_1": "NYG",
        "score_1": 20,
        "score_2": 33,
        "team_2": "DAL",
        "game_url": "usa/nfl-2010-2011/new-york-giants-dallas-cowboys-QXuF3Vrk/"
    },
    {
        "date": "07/Nov",
        "team_1": "SEA",
        "score_1": 7,
        "score_2": 41,
        "team_2": "NYG",
        "game_url": "usa/nfl-2010-2011/seattle-seahawks-new-york-giants-84eXbGi3/"
    },
    {
        "date": "25/Oct",
        "team_1": "DAL",
        "score_1": 35,
        "score_2": 41,
        "team_2": "NYG",
        "game_url": "usa/nfl-2010-2011/dallas-cowboys-new-york-giants-YRItBdWp/"
    },
    {
        "date": "17/Oct",
        "team_1": "NYG",
        "score_1": 28,
        "score_2": 20,
        "team_2": "DET",
        "game_url": "usa/nfl-2010-2011/new-york-giants-detroit-lions-EVuT5U3f/"
    },
    {
        "date": "10/Oct",
        "team_1": "HOU",
        "score_1": 10,
        "score_2": 34,
        "team_2": "NYG",
        "game_url": "usa/nfl-2010-2011/houston-texans-new-york-giants-EkrhE4VR/"
    },
    {
        "date": "03/Oct",
        "team_1": "NYG",
        "score_1": 17,
        "score_2": 3,
        "team_2": "CHI",
        "game_url": "usa/nfl-2010-2011/new-york-giants-chicago-bears-fanYe59q/"
    },
    {
        "date": "26/Sep",
        "team_1": "NYG",
        "score_1": 10,
        "score_2": 29,
        "team_2": "TEN",
        "game_url": "usa/nfl-2010-2011/new-york-giants-tennessee-titans-EV1TlHB5/"
    },
    {
        "date": "19/Sep",
        "team_1": "IND",
        "score_1": 38,
        "score_2": 14,
        "team_2": "NYG",
        "game_url": "usa/nfl-2010-2011/indianapolis-colts-new-york-giants-YseZzbs6/"
    },
    {
        "date": "12/Sep",
        "team_1": "NYG",
        "score_1": 31,
        "score_2": 18,
        "team_2": "CAR",
        "game_url": "usa/nfl-2010-2011/new-york-giants-carolina-panthers-G6f9WBa9/"
    },
    {
        "date": "02/Sep",
        "team_1": "NYG",
        "score_1": 20,
        "score_2": 17,
        "team_2": "NE",
        "game_url": "usa/nfl-2010-2011/new-york-giants-new-england-patriots-nLBUjA83/"
    },
    {
        "date": "28/Aug",
        "team_1": "BAL",
        "score_1": 24,
        "score_2": 10,
        "team_2": "NYG",
        "game_url": "usa/nfl-2010-2011/baltimore-ravens-new-york-giants-vRMcfrD4/"
    },
    {
        "date": "21/Aug",
        "team_1": "NYG",
        "score_1": 17,
        "score_2": 24,
        "team_2": "PIT",
        "game_url": "usa/nfl-2010-2011/new-york-giants-pittsburgh-steelers-OxccV7Un/"
    },
    {
        "date": "16/Aug",
        "team_1": "NYJ",
        "score_1": 16,
        "score_2": 31,
        "team_2": "NYG",
        "game_url": "usa/nfl-2010-2011/new-york-jets-new-york-giants-j1vQQhw1/"
    },
    {
        "date": "03/Jan",
        "team_1": "MIN",
        "score_1": 44,
        "score_2": 7,
        "team_2": "NYG",
        "game_url": "usa/nfl-2009-2010/minnesota-vikings-new-york-giants-ABlAwBS6/"
    },
    {
        "date": "27/Dec",
        "team_1": "NYG",
        "score_1": 9,
        "score_2": 41,
        "team_2": "CAR",
        "game_url": "usa/nfl-2009-2010/new-york-giants-carolina-panthers-G8ocWMUS/"
    },
    {
        "date": "21/Dec",
        "team_1": "WSH",
        "score_1": 12,
        "score_2": 45,
        "team_2": "NYG",
        "game_url": "usa/nfl-2009-2010/washington-commanders-new-york-giants-j3DQyR0i/"
    },
    {
        "date": "13/Dec",
        "team_1": "NYG",
        "score_1": 38,
        "score_2": 45,
        "team_2": "PHI",
        "game_url": "usa/nfl-2009-2010/new-york-giants-philadelphia-eagles-W8Vox4j9/"
    },
    {
        "date": "06/Dec",
        "team_1": "NYG",
        "score_1": 31,
        "score_2": 24,
        "team_2": "DAL",
        "game_url": "usa/nfl-2009-2010/new-york-giants-dallas-cowboys-C4bpOqKI/"
    },
    {
        "date": "26/Nov",
        "team_1": "DEN",
        "score_1": 26,
        "score_2": 6,
        "team_2": "NYG",
        "game_url": "usa/nfl-2009-2010/denver-broncos-new-york-giants-pQWGrQfh/"
    },
    {
        "date": "22/Nov",
        "team_1": "NYG",
        "score_1": 34,
        "score_2": 31,
        "team_2": "ATL",
        "game_url": "usa/nfl-2009-2010/new-york-giants-atlanta-falcons-44MdFhUr/"
    },
    {
        "date": "08/Nov",
        "team_1": "NYG",
        "score_1": 20,
        "score_2": 21,
        "team_2": "LAC",
        "game_url": "usa/nfl-2009-2010/new-york-giants-los-angeles-chargers-AV018Fpb/"
    },
    {
        "date": "01/Nov",
        "team_1": "PHI",
        "score_1": 40,
        "score_2": 17,
        "team_2": "NYG",
        "game_url": "usa/nfl-2009-2010/philadelphia-eagles-new-york-giants-MLUk7dtn/"
    },
    {
        "date": "25/Oct",
        "team_1": "NYG",
        "score_1": 17,
        "score_2": 24,
        "team_2": "ARI",
        "game_url": "usa/nfl-2009-2010/new-york-giants-arizona-cardinals-0b8icNRm/"
    },
    {
        "date": "18/Oct",
        "team_1": "NO",
        "score_1": 48,
        "score_2": 27,
        "team_2": "NYG",
        "game_url": "usa/nfl-2009-2010/new-orleans-saints-new-york-giants-0ICUfphb/"
    },
    {
        "date": "11/Oct",
        "team_1": "NYG",
        "score_1": 44,
        "score_2": 7,
        "team_2": "LV",
        "game_url": "usa/nfl-2009-2010/new-york-giants-las-vegas-raiders-dW2dGVAD/"
    },
    {
        "date": "04/Oct",
        "team_1": "KC",
        "score_1": 16,
        "score_2": 27,
        "team_2": "NYG",
        "game_url": "usa/nfl-2009-2010/kansas-city-chiefs-new-york-giants-8dVhDf0O/"
    },
    {
        "date": "27/Sep",
        "team_1": "TB",
        "score_1": 0,
        "score_2": 24,
        "team_2": "NYG",
        "game_url": "usa/nfl-2009-2010/tampa-bay-buccaneers-new-york-giants-2TN0GuT2/"
    },
    {
        "date": "20/Sep",
        "team_1": "DAL",
        "score_1": 31,
        "score_2": 33,
        "team_2": "NYG",
        "game_url": "usa/nfl-2009-2010/dallas-cowboys-new-york-giants-2FjoX3zm/"
    },
    {
        "date": "13/Sep",
        "team_1": "NYG",
        "score_1": 23,
        "score_2": 17,
        "team_2": "WSH",
        "game_url": "usa/nfl-2009-2010/new-york-giants-washington-commanders-fJz16gcp/"
    },
    {
        "date": "03/Sep",
        "team_1": "NE",
        "score_1": 38,
        "score_2": 27,
        "team_2": "NYG",
        "game_url": "usa/nfl-2009-2010/new-england-patriots-new-york-giants-nwqzQTjK/"
    },
    {
        "date": "29/Aug",
        "team_1": "NYG",
        "score_1": 25,
        "score_2": 27,
        "team_2": "NYJ",
        "game_url": "usa/nfl-2009-2010/new-york-giants-new-york-jets-ncXQfDlm/"
    },
    {
        "date": "22/Aug",
        "team_1": "CHI",
        "score_1": 17,
        "score_2": 3,
        "team_2": "NYG",
        "game_url": "usa/nfl-2009-2010/chicago-bears-new-york-giants-rDA63ZjN/"
    },
    {
        "date": "17/Aug",
        "team_1": "NYG",
        "score_1": 24,
        "score_2": 17,
        "team_2": "CAR",
        "game_url": "usa/nfl-2009-2010/new-york-giants-carolina-panthers-2ccz22eC/"
    },
    {
        "date": "11/Jan",
        "team_1": "NYG",
        "score_1": 11,
        "score_2": 23,
        "team_2": "PHI",
        "game_url": "usa/nfl-2008-2009/new-york-giants-philadelphia-eagles-Y14jihDg/"
    },
    {
        "date": "28/Dec",
        "team_1": "MIN",
        "score_1": 20,
        "score_2": 19,
        "team_2": "NYG",
        "game_url": "usa/nfl-2008-2009/minnesota-vikings-new-york-giants-UB2nHiyR/"
    },
    {
        "date": "21/Dec",
        "team_1": "NYG",
        "score_1": 34,
        "score_2": 28,
        "team_2": "CAR",
        "game_url": "usa/nfl-2008-2009/new-york-giants-carolina-panthers-hABM7c1C/"
    },
    {
        "date": "14/Dec",
        "team_1": "DAL",
        "score_1": 20,
        "score_2": 8,
        "team_2": "NYG",
        "game_url": "usa/nfl-2008-2009/dallas-cowboys-new-york-giants-G8Cno3mH/"
    },
    {
        "date": "07/Dec",
        "team_1": "NYG",
        "score_1": 14,
        "score_2": 20,
        "team_2": "PHI",
        "game_url": "usa/nfl-2008-2009/new-york-giants-philadelphia-eagles-Q7PEyb7p/"
    },
    {
        "date": "30/Nov",
        "team_1": "WSH",
        "score_1": 7,
        "score_2": 23,
        "team_2": "NYG",
        "game_url": "usa/nfl-2008-2009/washington-commanders-new-york-giants-ELi9HGbF/"
    },
    {
        "date": "23/Nov",
        "team_1": "ARI",
        "score_1": 29,
        "score_2": 37,
        "team_2": "NYG",
        "game_url": "usa/nfl-2008-2009/arizona-cardinals-new-york-giants-KffXgEH2/"
    },
    {
        "date": "16/Nov",
        "team_1": "NYG",
        "score_1": 30,
        "score_2": 10,
        "team_2": "BAL",
        "game_url": "usa/nfl-2008-2009/new-york-giants-baltimore-ravens-jTsgGcqt/"
    },
    {
        "date": "09/Nov",
        "team_1": "PHI",
        "score_1": 31,
        "score_2": 36,
        "team_2": "NYG",
        "game_url": "usa/nfl-2008-2009/philadelphia-eagles-new-york-giants-bwVROnDs/"
    },
    {
        "date": "02/Nov",
        "team_1": "NYG",
        "score_1": 35,
        "score_2": 14,
        "team_2": "DAL",
        "game_url": "usa/nfl-2008-2009/new-york-giants-dallas-cowboys-dxJ1GmQu/"
    },
    {
        "date": "26/Oct",
        "team_1": "PIT",
        "score_1": 14,
        "score_2": 21,
        "team_2": "NYG",
        "game_url": "usa/nfl-2008-2009/pittsburgh-steelers-new-york-giants-xSMtwgyA/"
    },
    {
        "date": "19/Oct",
        "team_1": "NYG",
        "score_1": 29,
        "score_2": 17,
        "team_2": "SF",
        "game_url": "usa/nfl-2008-2009/new-york-giants-san-francisco-49ers-CSTvMuwJ/"
    },
    {
        "date": "13/Oct",
        "team_1": "CLE",
        "score_1": 35,
        "score_2": 14,
        "team_2": "NYG",
        "game_url": "usa/nfl-2008-2009/cleveland-browns-new-york-giants-xbqA4Mgl/"
    },
    {
        "date": "05/Oct",
        "team_1": "NYG",
        "score_1": 44,
        "score_2": 6,
        "team_2": "SEA",
        "game_url": "usa/nfl-2008-2009/new-york-giants-seattle-seahawks-ILQBogB2/"
    },
    {
        "date": "21/Sep",
        "team_1": "NYG",
        "score_1": 26,
        "score_2": 23,
        "team_2": "CIN",
        "game_url": "usa/nfl-2008-2009/new-york-giants-cincinnati-bengals-t65B6tdQ/"
    },
    {
        "date": "04/Sep",
        "team_1": "WSH",
        "score_1": 7,
        "score_2": 16,
        "team_2": "NYG",
        "game_url": "usa/nfl-2008-2009/washington-commanders-new-york-giants-M3sLhQB0/"
    }
]